argparse_prompt.py
argparse_prompt-0.0.5.dist-info/LICENSE
argparse_prompt-0.0.5.dist-info/METADATA
argparse_prompt-0.0.5.dist-info/WHEEL
argparse_prompt-0.0.5.dist-info/top_level.txt
argparse_prompt-0.0.5.dist-info/RECORD
