Metadata-Version: 2.1
Name: argparse-prompt
Version: 0.0.5
Summary: Wrapper for the built-in Argparse, allowing missing command-line arguments to be filled in by the user via interactive prompts
Home-page: https://github.com/MelbourneGenomics/ArgparsePrompt
Author: Michael Milton
Author-email: michael.r.milton@gmail.com
License: GPL
Keywords: argparse prompt interactive argument
Platform: UNKNOWN
Classifier: Development Status :: 5 - Production/Stable
Classifier: Environment :: Console
Classifier: License :: OSI Approved :: GNU General Public License v3 (GPLv3)
Classifier: Operating System :: OS Independent
Classifier: Topic :: Software Development :: User Interfaces
Classifier: Programming Language :: Python :: 3 :: Only
